ai_haley_kg_domain/__init__.py
ai_haley_kg_domain/domain-ontology/haley-ai-kg-0.1.0.owl
ai_haley_kg_domain/model/DomainCategory.py
ai_haley_kg_domain/model/DomainCategory.pyi
ai_haley_kg_domain/model/DomainOntology.py
ai_haley_kg_domain/model/Edge_hasActorKGFrame.py
ai_haley_kg_domain/model/Edge_hasActorKGFrame.pyi
ai_haley_kg_domain/model/Edge_hasAgentKGFrame.py
ai_haley_kg_domain/model/Edge_hasAgentKGFrame.pyi
ai_haley_kg_domain/model/Edge_hasChatMessageKGFrame.py
ai_haley_kg_domain/model/Edge_hasChatMessageKGFrame.pyi
ai_haley_kg_domain/model/Edge_hasDocumentKGFrame.py
ai_haley_kg_domain/model/Edge_hasDocumentKGFrame.pyi
ai_haley_kg_domain/model/Edge_hasEntityKGFrame.py
ai_haley_kg_domain/model/Edge_hasEntityKGFrame.pyi
ai_haley_kg_domain/model/Edge_hasEntityKGStatement.py
ai_haley_kg_domain/model/Edge_hasEntityKGStatement.pyi
ai_haley_kg_domain/model/Edge_hasEntityTypePartOfKGFrameType.py
ai_haley_kg_domain/model/Edge_hasEntityTypePartOfKGFrameType.pyi
ai_haley_kg_domain/model/Edge_hasEventKGFrame.py
ai_haley_kg_domain/model/Edge_hasEventKGFrame.pyi
ai_haley_kg_domain/model/Edge_hasGroupKGFrame.py
ai_haley_kg_domain/model/Edge_hasGroupKGFrame.pyi
ai_haley_kg_domain/model/Edge_hasIncomingKGRelationType.py
ai_haley_kg_domain/model/Edge_hasIncomingKGRelationType.pyi
ai_haley_kg_domain/model/Edge_hasInteractionKGDocument.py
ai_haley_kg_domain/model/Edge_hasInteractionKGDocument.pyi
ai_haley_kg_domain/model/Edge_hasInteractionKGEntity.py
ai_haley_kg_domain/model/Edge_hasInteractionKGEntity.pyi
ai_haley_kg_domain/model/Edge_hasInteractionKGFrame.py
ai_haley_kg_domain/model/Edge_hasInteractionKGFrame.pyi
ai_haley_kg_domain/model/Edge_hasKGAction.py
ai_haley_kg_domain/model/Edge_hasKGAction.pyi
ai_haley_kg_domain/model/Edge_hasKGActor.py
ai_haley_kg_domain/model/Edge_hasKGActor.pyi
ai_haley_kg_domain/model/Edge_hasKGAgent.py
ai_haley_kg_domain/model/Edge_hasKGAgent.pyi
ai_haley_kg_domain/model/Edge_hasKGAgentDuplicate.py
vital_ai_haley_kg-0.1.24.dist-info/METADATA
vital_ai_haley_kg-0.1.24.dist-info/WHEEL
vital_ai_haley_kg-0.1.24.dist-info/entry_points.txt
vital_ai_haley_kg-0.1.24.dist-info/top_level.txt
vital_ai_haley_kg-0.1.24.dist-info/RECORD
