Metadata-Version: 2.1
Name: vital-ai-haley-kg
Version: 0.1.24
Summary: VitalSigns haley kg domain
Home-page: https://github.com/vital-ai/vitalhome-haley
Author: Marc Hadfield
Author-email: marc@vital.ai
License: Apache License 2.0
Classifier: Programming Language :: Python :: 3.10
Classifier: License :: OSI Approved :: Apache Software License
Classifier: Operating System :: OS Independent
Requires-Python: >=3.10
Requires-Dist: vital-ai-haley >=0.1.7
Requires-Dist: vital-ai-haley-question >=0.1.6
Requires-Dist: vital-ai-vitalsigns >=0.1.21
